LICENSE
README.md
pyproject.toml
setup.py
src/Match_aidil/__init__.py
src/Match_aidil/aritmatika.py
src/Match_aidil/bangun_ruang.py
src/Match_package_aidil.egg-info/PKG-INFO
src/Match_package_aidil.egg-info/SOURCES.txt
src/Match_package_aidil.egg-info/dependency_links.txt
src/Match_package_aidil.egg-info/top_level.txt