Metadata-Version: 2.1
Name: Match-package-aidil
Version: 0.2.0
Summary: Matematika untuk python
Home-page: https://github.com/pypa/sampleproject
Author: aidil
Author-email: aidil@gmail.com
License: UNKNOWN
Project-URL: Bug Tracker, https://github.com/pypa/sampleproject/issues
Platform: UNKNOWN
Classifier: Programming Language :: Python :: 3
Classifier: License :: OSI Approved :: MIT License
Classifier: Operating System :: OS Independent
Requires-Python: >=3.6
License-File: LICENSE
